setup.py
robotp2p/__init__.py
robotp2p.egg-info/PKG-INFO
robotp2p.egg-info/SOURCES.txt
robotp2p.egg-info/dependency_links.txt
robotp2p.egg-info/not-zip-safe
robotp2p.egg-info/requires.txt
robotp2p.egg-info/top_level.txt