Metadata-Version: 1.1
Name: robotp2p
Version: 0.102
Summary: distributed robot control system
Home-page: http://github.com/jordankubica/robotp2p
Author: Jordan Kubica
Author-email: jordan.kubica+github@gmail.com
License: MIT
Platform: UNKNOWN
Classifier: Development Status :: 1 - Planning
